odoo/addons/partner_communication/README.rst
odoo/addons/partner_communication/__init__.py
odoo/addons/partner_communication/__manifest__.py
odoo/addons/partner_communication/i18n/es.po
odoo/addons/partner_communication/models/__init__.py
odoo/addons/partner_communication/models/account_move.py
odoo/addons/partner_communication/models/partner_communication_channel.py
odoo/addons/partner_communication/models/partner_communication_channel_mixin.py
odoo/addons/partner_communication/models/purchase_order.py
odoo/addons/partner_communication/models/res_partner.py
odoo/addons/partner_communication/models/sale_order.py
odoo/addons/partner_communication/models/stock_picking.py
odoo/addons/partner_communication/security/ir.model.access.csv
odoo/addons/partner_communication/static/description/icon.png
odoo/addons/partner_communication/views/account_move_views.xml
odoo/addons/partner_communication/views/partner_communication_channel_views.xml
odoo/addons/partner_communication/views/purchase_views.xml
odoo/addons/partner_communication/views/res_partner_views.xml
odoo/addons/partner_communication/views/sale_order_views.xml
odoo/addons/partner_communication/views/stock_picking_views.xml
odoo_addon_partner_communication-16.0.1.0.0.2.dist-info/METADATA
odoo_addon_partner_communication-16.0.1.0.0.2.dist-info/WHEEL
odoo_addon_partner_communication-16.0.1.0.0.2.dist-info/top_level.txt
odoo_addon_partner_communication-16.0.1.0.0.2.dist-info/RECORD
